odoo/addons/default_multi_user/README.rst
odoo/addons/default_multi_user/__init__.py
odoo/addons/default_multi_user/__manifest__.py
odoo/addons/default_multi_user/hooks.py
odoo/addons/default_multi_user/i18n/default_multi_user.pot
odoo/addons/default_multi_user/i18n/es.po
odoo/addons/default_multi_user/i18n/it.po
odoo/addons/default_multi_user/i18n/pt.po
odoo/addons/default_multi_user/models/__init__.py
odoo/addons/default_multi_user/models/ir_default.py
odoo/addons/default_multi_user/readme/CONFIGURE.md
odoo/addons/default_multi_user/readme/CONTRIBUTORS.md
odoo/addons/default_multi_user/readme/DESCRIPTION.md
odoo/addons/default_multi_user/static/description/icon.png
odoo/addons/default_multi_user/static/description/index.html
odoo/addons/default_multi_user/tests/__init__.py
odoo/addons/default_multi_user/tests/test_default_multi_user.py
odoo/addons/default_multi_user/views/ir_default_view.xml
odoo_addon_default_multi_user-18.0.1.0.0.3.dist-info/METADATA
odoo_addon_default_multi_user-18.0.1.0.0.3.dist-info/WHEEL
odoo_addon_default_multi_user-18.0.1.0.0.3.dist-info/top_level.txt
odoo_addon_default_multi_user-18.0.1.0.0.3.dist-info/RECORD
